textfairy/__init__.py
textfairy/cli.py
textfairy/textfairy.py
textfairy-0.1.0.dist-info/DESCRIPTION.rst
textfairy-0.1.0.dist-info/METADATA
textfairy-0.1.0.dist-info/RECORD
textfairy-0.1.0.dist-info/WHEEL
textfairy-0.1.0.dist-info/entry_points.txt
textfairy-0.1.0.dist-info/metadata.json
textfairy-0.1.0.dist-info/top_level.txt
