Metadata-Version: 2.0
Name: textfairy
Version: 0.1.0
Summary: textfairy converts your text to UTF-8
Home-page: https://git.nzoss.org.nz/tim-mcnamara/textfairy
Author: Tim McNamara
Author-email: paperless@timmcnamara.co.nz
License: MIT license
Keywords: textfairy
Platform: UNKNOWN
Classifier: Development Status :: 2 - Pre-Alpha
Classifier: Intended Audience :: Developers
Classifier: License :: OSI Approved :: MIT License
Classifier: Natural Language :: English
Classifier: Topic :: Utilities
Classifier: Topic :: Text Processing :: General
Classifier: Programming Language :: Python :: 2
Classifier: Programming Language :: Python :: 2.6
Classifier: Programming Language :: Python :: 2.7
Requires-Dist: Click (>=6.0)
Requires-Dist: chardet
